cyphertune/__init__.py
cyphertune/inference.py
cyphertune/models.py
cyphertune/train.py
cyphertune/utils.py
tllm/__init__.py
tllm/inference.py
tllm/models.py
tllm/train.py
tllm/utils.py
trainllm-0.0.4.dist-info/LICENSE
trainllm-0.0.4.dist-info/METADATA
trainllm-0.0.4.dist-info/WHEEL
trainllm-0.0.4.dist-info/top_level.txt
trainllm-0.0.4.dist-info/RECORD
