Metadata-Version: 2.1
Name: trainllm
Version: 0.0.4
Summary: Fine-tuning LLMs for instruction using QLoRA.
Home-page: UNKNOWN
Author: InquestGeronimo
Author-email: rcostanl@gmail.com
License: Apache 2.0 license
Keywords: llms,training,fine-tuning,LLM,NLP
Platform: UNKNOWN
Classifier: Development Status :: 1 - Planning
Classifier: Intended Audience :: Developers
Classifier: Programming Language :: Python :: 3
Classifier: Operating System :: Unix
License-File: LICENSE
Requires-Dist: accelerate >=0.27.0
Requires-Dist: bitsandbytes >=0.42.0
Requires-Dist: datasets >=2.17.0
Requires-Dist: peft >=0.8.2
Requires-Dist: pydantic >=2.6.1
Requires-Dist: scipy >=1.11.4
Requires-Dist: transformers >=4.37.2
Requires-Dist: wandb >=0.16.3
